{"trial_id": "fcad678e591e8016ec0ec82d51f1f1b3", "hyperparameters": {"space": [{"class_name": "Int", "config": {"name": "layers", "default": null, "conditions": [], "min_value": 0, "max_value": 2, "step": 1, "sampling": null}}, {"class_name": "Int", "config": {"name": "batch_size", "default": null, "conditions": [], "min_value": 1, "max_value": 501, "step": 5, "sampling": null}}, {"class_name": "Int", "config": {"name": "units_0", "default": null, "conditions": [], "min_value": 1, "max_value": 201, "step": 2, "sampling": null}}, {"class_name": "Choice", "config": {"name": "act_0", "default": "relu", "conditions": [], "values": ["relu", "sigmoid", "selu"], "ordered": false}}, {"class_name": "Int", "config": {"name": "units_1", "default": null, "conditions": [], "min_value": 1, "max_value": 201, "step": 2, "sampling": null}}, {"class_name": "Choice", "config": {"name": "act_1", "default": "relu", "conditions": [], "values": ["relu", "sigmoid", "selu"], "ordered": false}}], "values": {"layers": 2, "batch_size": 281, "units_0": 81, "act_0": "selu", "units_1": 83, "act_1": "relu", "tuner/epochs": 25, "tuner/initial_epoch": 9, "tuner/bracket": 5, "tuner/round": 1, "tuner/trial_id": "011863233b2b4971570ad6b0100d0839"}}, "metrics": {"metrics": {"loss": {"direction": "min", "observations": [{"value": [26303.3203125], "step": 0}]}, "accuracy": {"direction": "max", "observations": [{"value": [0.0], "step": 0}]}, "val_loss": {"direction": "min", "observations": [{"value": [27430.994140625], "step": 0}]}, "val_accuracy": {"direction": "max", "observations": [{"value": [0.0], "step": 0}]}}}, "score": 27430.994140625, "best_step": 0, "status": "COMPLETED"}