{"ongoing_trials": {"tuner0": "68c533ab6f72501e3cea7bc070a0831f"}, "hyperparameters": {"space": [{"class_name": "Int", "config": {"name": "layers", "default": null, "conditions": [], "min_value": 0, "max_value": 10, "step": 1, "sampling": null}}], "values": {"layers": 0}}, "seed": 3496, "seed_state": 3497, "tried_so_far": ["364f33e2e83c4a79406a71518c4afc1c"], "hyperband_iterations": 1, "max_epochs": 200, "min_epochs": 1, "factor": 3, "brackets": [{"bracket_num": 4, "rounds": [[{"past_id": null, "id": "68c533ab6f72501e3cea7bc070a0831f"}], [], [], [], []]}], "current_bracket": 4, "current_iteration": 0}