{"trial_id": "9b0e6fb62a8cb9d493d8fec1e552a183", "hyperparameters": {"space": [{"class_name": "Int", "config": {"name": "layers", "default": null, "conditions": [], "min_value": 0, "max_value": 2, "step": 1, "sampling": null}}, {"class_name": "Int", "config": {"name": "batch_size", "default": null, "conditions": [], "min_value": 1, "max_value": 501, "step": 5, "sampling": null}}, {"class_name": "Int", "config": {"name": "units_0", "default": null, "conditions": [], "min_value": 1, "max_value": 301, "step": 3, "sampling": null}}, {"class_name": "Choice", "config": {"name": "act_0", "default": "relu", "conditions": [], "values": ["relu", "sigmoid", "selu"], "ordered": false}}, {"class_name": "Int", "config": {"name": "units_1", "default": null, "conditions": [], "min_value": 1, "max_value": 301, "step": 3, "sampling": null}}, {"class_name": "Choice", "config": {"name": "act_1", "default": "relu", "conditions": [], "values": ["relu", "sigmoid", "selu"], "ordered": false}}], "values": {"layers": 2, "batch_size": 71, "units_0": 76, "act_0": "selu", "units_1": 271, "act_1": "relu", "tuner/epochs": 13, "tuner/initial_epoch": 5, "tuner/bracket": 5, "tuner/round": 1, "tuner/trial_id": "efff694af17561b0543d3a64925c9f82"}}, "metrics": {"metrics": {"loss": {"direction": "min", "observations": [{"value": [24139.279296875], "step": 0}]}, "mean_squared_error": {"direction": "min", "observations": [{"value": [24139.279296875], "step": 0}]}, "val_loss": {"direction": "min", "observations": [{"value": [26060.662109375], "step": 0}]}, "val_mean_squared_error": {"direction": "min", "observations": [{"value": [26060.662109375], "step": 0}]}}}, "score": 26060.662109375, "best_step": 0, "status": "COMPLETED"}